tsax/__init__.py
tsax/__main__.py
tsax/downloader.py
tsax-1.0.1.dist-info/METADATA
tsax-1.0.1.dist-info/WHEEL
tsax-1.0.1.dist-info/entry_points.txt
tsax-1.0.1.dist-info/top_level.txt
tsax-1.0.1.dist-info/RECORD
